_test/scratch.py
docxlatex/__init__.py
docxlatex/cleaners.py
docxlatex/cli.py
docxlatex/docxlatex.py
docxlatex/parser/__init__.py
docxlatex/parser/ommlparser.py
docxlatex/parser/utils.py
docxlatex-1.0.0.dist-info/licenses/LICENSE
tests/__init__.py
tests/test_simple_text_extraction.py
tests/omml/__init__.py
tests/omml/test_symbols.py
tests/omml/test_tags.py
venv/Lib/site-packages/__editable___docxlatex_0_1_6_finder.py
venv/Lib/site-packages/_black_version.py
venv/Lib/site-packages/_virtualenv.py
venv/Lib/site-packages/mypy_extensions.py
venv/Lib/site-packages/_distutils_hack/__init__.py
venv/Lib/site-packages/_distutils_hack/override.py
venv/Lib/site-packages/black/__init__.py
venv/Lib/site-packages/black/__main__.py
venv/Lib/site-packages/black/_width_table.py
venv/Lib/site-packages/black/brackets.py
venv/Lib/site-packages/black/cache.py
venv/Lib/site-packages/black/comments.py
venv/Lib/site-packages/black/concurrency.py
venv/Lib/site-packages/black/const.py
venv/Lib/site-packages/black/debug.py
venv/Lib/site-packages/black/files.py
venv/Lib/site-packages/black/handle_ipynb_magics.py
venv/Lib/site-packages/black/linegen.py
venv/Lib/site-packages/black/lines.py
venv/Lib/site-packages/black/mode.py
venv/Lib/site-packages/black/nodes.py
venv/Lib/site-packages/black/numerics.py
venv/Lib/site-packages/black/output.py
venv/Lib/site-packages/black/parsing.py
venv/Lib/site-packages/black/py.typed
venv/Lib/site-packages/black/ranges.py
venv/Lib/site-packages/black/report.py
venv/Lib/site-packages/black/rusty.py
venv/Lib/site-packages/black/strings.py
venv/Lib/site-packages/black/trans.py
venv/Lib/site-packages/blackd/__init__.py
venv/Lib/site-packages/blackd/__main__.py
venv/Lib/site-packages/blackd/middlewares.py
venv/Lib/site-packages/blib2to3/__init__.py
venv/Lib/site-packages/blib2to3/pygram.py
venv/Lib/site-packages/blib2to3/pytree.py
venv/Lib/site-packages/blib2to3/pgen2/__init__.py
venv/Lib/site-packages/blib2to3/pgen2/conv.py
venv/Lib/site-packages/blib2to3/pgen2/driver.py
docxlatex-1.0.0.dist-info/METADATA
docxlatex-1.0.0.dist-info/WHEEL
docxlatex-1.0.0.dist-info/entry_points.txt
docxlatex-1.0.0.dist-info/top_level.txt
docxlatex-1.0.0.dist-info/RECORD
